scrapper.py
setup.py
tests.py
Scrapper.egg-info/PKG-INFO
Scrapper.egg-info/SOURCES.txt
Scrapper.egg-info/dependency_links.txt
Scrapper.egg-info/requires.txt
Scrapper.egg-info/top_level.txt