Metadata-Version: 1.1
Name: Scrapper
Version: 0.9.5
Summary: Scrapper is small, Python web scraping library
Home-page: https://github.com/Alkemic/scrapper
Author: Daniel Alkemic Czuba
Author-email: alkemic7@gmail.com
License: MIT
Keywords: scrapper,scraping,webscraping
Platform: UNKNOWN
Classifier: Development Status :: 4 - Beta
Classifier: Intended Audience :: Developers
Classifier: License :: OSI Approved :: MIT License
Classifier: Programming Language :: Python
Classifier: Programming Language :: Python :: 3
Classifier: Programming Language :: Python :: 3.3
Classifier: Programming Language :: Python :: 3.4
Classifier: Programming Language :: Python :: 3.5
Classifier: Programming Language :: Python :: 3.6
Classifier: Topic :: Internet :: WWW/HTTP
Classifier: Topic :: Internet :: WWW/HTTP :: Indexing/Search
Classifier: Topic :: Software Development :: Libraries :: Python Modules
